setup.cfg
setup.py
miac_logger/__init__.py
miac_logger/logger.py
miac_logger.egg-info/PKG-INFO
miac_logger.egg-info/SOURCES.txt
miac_logger.egg-info/dependency_links.txt
miac_logger.egg-info/not-zip-safe
miac_logger.egg-info/top_level.txt