Metadata-Version: 2.1
Name: miac-logger
Version: 0.1
Summary: Simple logger
Home-page: UNKNOWN
Author-email: arhdomain@gmail.com
License: UNKNOWN
Platform: UNKNOWN
